{
  "Gap Up Momentum Top": [
    {
      "ticker": "MOTHERSON",
      "name": "MOTHERSON",
      "current_price": 74.21216583251953,
      "change_rate": 1.3471046205793717,
      "volume": 17735347,
      "trade_value": 1316178512.6612778,
      "agent_fit_score": 1.0,
      "risk_reward_ratio": 3.0,
      "stop_loss_pct": 5.0,
      "stop_loss_price": 70.50155754089356,
      "target_price": 85.34399070739745,
      "quality_score": 59.69166666666666,
      "quality_signal": "HOLD",
      "quality_reasons": "Expensive valuation (PE 40.7); Golden cross (50MA > 200MA); Trading near 52-week high",
      "final_score": 0.6387666666666667,
      "metrics": {
        "sector": "Consumer Cyclical",
        "industry": "Auto Parts",
        "market_cap_cr": 138475.0,
        "trailing_pe": 40.7,
        "forward_pe": 26.3,
        "price_to_book": 3.75,
        "dividend_yield_pct": 45.0,
        "revenue_growth_pct": 14.5,
        "earnings_growth_pct": 16.4,
        "operating_margin_pct": 5.5,
        "profit_margin_pct": 2.8,
        "roe_pct": null,
        "rsi_14": 55.9,
        "sma_50": 119.29,
        "sma_200": 113.76,
        "pct_from_52w_high": -3.4,
        "beta": 0.98,
        "analyst_recommendation": "none",
        "target_mean": 139.91,
        "target_upside_pct": 6.4,
        "analyst_count": 22,
        "debt_to_equity": 49.9,
        "valuation_score": 52.0,
        "growth_score": 68.0,
        "profitability_score": 32.0,
        "technical_score": 69.0,
        "analyst_score": 68.0,
        "risk_score": 65.0
      }
    }
  ],
  "Value-to-Cap Ratio Top": [
    {
      "ticker": "ZENSARTECH",
      "name": "ZENSARTECH",
      "current_price": 567.482666015625,
      "change_rate": 5.3054123755126446,
      "volume": 6076286,
      "trade_value": 3448186978.753418,
      "agent_fit_score": 1.0,
      "risk_reward_ratio": 2.999999999999992,
      "stop_loss_pct": 5.0,
      "stop_loss_price": 539.1085327148437,
      "target_price": 652.6050659179687,
      "quality_score": 54.366666666666674,
      "quality_signal": "HOLD",
      "quality_reasons": "Attractively valued (PE 14.7); Death cross (50MA < 200MA); Down 45% from 52W high",
      "final_score": 0.8174666666666668,
      "metrics": {
        "sector": "Technology",
        "industry": "Information Technology Services",
        "market_cap_cr": 11197.0,
        "trailing_pe": 14.7,
        "forward_pe": 12.7,
        "price_to_book": 2.37,
        "dividend_yield_pct": 276.0,
        "revenue_growth_pct": 6.7,
        "earnings_growth_pct": 19.2,
        "operating_margin_pct": 14.7,
        "profit_margin_pct": 7.3,
        "roe_pct": null,
        "rsi_14": 33.1,
        "sma_50": 542.15,
        "sma_200": 679.36,
        "pct_from_52w_high": -44.8,
        "beta": null,
        "analyst_recommendation": "none",
        "target_mean": 614.83,
        "target_upside_pct": 24.5,
        "analyst_count": 12,
        "debt_to_equity": 1.7,
        "valuation_score": 72.0,
        "growth_score": 58.0,
        "profitability_score": 52.0,
        "technical_score": 39.0,
        "analyst_score": 70.0,
        "risk_score": 85.0
      }
    },
    {
      "ticker": "TATASTEEL",
      "name": "TATASTEEL",
      "current_price": 143.3992919921875,
      "change_rate": 5.6457269019104395,
      "volume": 166913078,
      "trade_value": 23935217209.436768,
      "agent_fit_score": 1.0,
      "risk_reward_ratio": 2.999999999999992,
      "stop_loss_pct": 5.0,
      "stop_loss_price": 136.2293273925781,
      "target_price": 164.9091857910156,
      "quality_score": 62.10833333333334,
      "quality_signal": "HOLD",
      "quality_reasons": "Golden cross (50MA > 200MA); Analyst: Buy; Target ₹223 (+6% upside)",
      "final_score": 0.7898799110818465,
      "metrics": {
        "sector": "Basic Materials",
        "industry": "Steel",
        "market_cap_cr": 261023.0,
        "trailing_pe": 28.5,
        "forward_pe": 11.1,
        "price_to_book": 2.75,
        "dividend_yield_pct": 191.0,
        "revenue_growth_pct": 12.5,
        "earnings_growth_pct": 125.4,
        "operating_margin_pct": 10.4,
        "profit_margin_pct": 4.7,
        "roe_pct": 11.2,
        "rsi_14": 47.5,
        "sma_50": 204.08,
        "sma_200": 184.78,
        "pct_from_52w_high": -6.7,
        "beta": 0.79,
        "analyst_recommendation": "buy",
        "target_mean": 222.68,
        "target_upside_pct": 6.4,
        "analyst_count": 34,
        "debt_to_equity": 89.0,
        "valuation_score": 65.0,
        "growth_score": 75.0,
        "profitability_score": 45.0,
        "technical_score": 65.0,
        "analyst_score": 67.0,
        "risk_score": 62.0
      }
    },
    {
      "ticker": "TATAPOWER",
      "name": "TATAPOWER",
      "current_price": 388.652099609375,
      "change_rate": 3.1516806982013463,
      "volume": 34069247,
      "trade_value": 13241084378.6604,
      "agent_fit_score": 1.0,
      "risk_reward_ratio": 2.999999999999991,
      "stop_loss_pct": 5.0,
      "stop_loss_price": 369.2194946289062,
      "target_price": 446.9499145507812,
      "quality_score": 54.324999999999996,
      "quality_signal": "HOLD",
      "quality_reasons": "Expensive valuation (PE 35.4); Revenue declining (-12.8%); Golden cross (50MA > 200MA)",
      "final_score": 0.7033780293516811,
      "metrics": {
        "sector": "Utilities",
        "industry": "Utilities - Independent Power Producers",
        "market_cap_cr": 132607.0,
        "trailing_pe": 35.4,
        "forward_pe": 27.4,
        "price_to_book": 3.5,
        "dividend_yield_pct": 62.0,
        "revenue_growth_pct": -12.8,
        "earnings_growth_pct": -4.6,
        "operating_margin_pct": 8.9,
        "profit_margin_pct": 6.0,
        "roe_pct": 11.3,
        "rsi_14": 37.7,
        "sma_50": 411.27,
        "sma_200": 389.58,
        "pct_from_52w_high": -10.7,
        "beta": 0.37,
        "analyst_recommendation": "buy",
        "target_mean": 428.7,
        "target_upside_pct": 3.3,
        "analyst_count": 24,
        "debt_to_equity": 167.8,
        "valuation_score": 58.0,
        "growth_score": 15.0,
        "profitability_score": 52.0,
        "technical_score": 68.0,
        "analyst_score": 62.0,
        "risk_score": 58.0
      }
    },
    {
      "ticker": "SBIN",
      "name": "SBIN",
      "current_price": 692.2653198242188,
      "change_rate": -0.12979870414383748,
      "volume": 18145126,
      "trade_value": 12561241453.640747,
      "agent_fit_score": 1.0,
      "risk_reward_ratio": 2.999999999999997,
      "stop_loss_pct": 5.0,
      "stop_loss_price": 657.6520538330078,
      "target_price": 796.1051177978514,
      "quality_score": 62.825,
      "quality_signal": "HOLD",
      "quality_reasons": "Attractively valued (PE 10.4); Highly profitable (margin 22.3%); Oversold (RSI 30)",
      "final_score": 0.6513,
      "metrics": {
        "sector": "Financial Services",
        "industry": "Banks - Regional",
        "market_cap_cr": 875801.0,
        "trailing_pe": 10.4,
        "forward_pe": 9.1,
        "price_to_book": 1.48,
        "dividend_yield_pct": 185.0,
        "revenue_growth_pct": 3.8,
        "earnings_growth_pct": -3.1,
        "operating_margin_pct": 26.8,
        "profit_margin_pct": 22.3,
        "roe_pct": 15.5,
        "rsi_14": 29.7,
        "sma_50": 1050.41,
        "sma_200": 988.05,
        "pct_from_52w_high": -23.2,
        "beta": 0.47,
        "analyst_recommendation": "strong_buy",
        "target_mean": 1195.0,
        "target_upside_pct": 25.9,
        "analyst_count": 38,
        "debt_to_equity": null,
        "valuation_score": 78.0,
        "growth_score": 28.0,
        "profitability_score": 83.0,
        "technical_score": 59.0,
        "analyst_score": 80.0,
        "risk_score": 85.0
      }
    }
  ],
  "screening_summary": {
    "total_tickers_scanned": 288,
    "snapshot_count": 283,
    "prev_snapshot_count": 283,
    "baseline_count": 283,
    "market_cap_count": 50,
    "triggers": {
      "Gap Up Momentum Top": {
        "candidate_count": 1,
        "top_candidates": [
          {
            "ticker": "MOTHERSON",
            "name": "MOTHERSON",
            "price": 74.21216583251953,
            "change_pct": 1.3471046205793717,
            "composite_score": 0.7124010563962302,
            "volume_surge_ratio": 0
          }
        ]
      },
      "Value-to-Cap Ratio Top": {
        "candidate_count": 6,
        "top_candidates": [
          {
            "ticker": "ZENSARTECH",
            "name": "ZENSARTECH",
            "price": 567.482666015625,
            "change_pct": 5.3054123755126446,
            "composite_score": 0.9711305601907826,
            "volume_surge_ratio": 0
          },
          {
            "ticker": "TATASTEEL",
            "name": "TATASTEEL",
            "price": 143.3992919921875,
            "change_pct": 5.6457269019104395,
            "composite_score": 0.7580448226672911,
            "volume_surge_ratio": 0
          },
          {
            "ticker": "TATAPOWER",
            "name": "TATAPOWER",
            "price": 388.652099609375,
            "change_pct": 3.1516806982013463,
            "composite_score": 0.55654937599518,
            "volume_surge_ratio": 0
          },
          {
            "ticker": "RELIANCE",
            "name": "RELIANCE",
            "price": 1428.8990478515625,
            "change_pct": 1.498351649304502,
            "composite_score": 0.24766502821331357,
            "volume_surge_ratio": 0
          },
          {
            "ticker": "SBIN",
            "name": "SBIN",
            "price": 692.2653198242188,
            "change_pct": -0.12979870414383748,
            "composite_score": 0.2432969705218868,
            "volume_surge_ratio": 0
          },
          {
            "ticker": "SAIL",
            "name": "SAIL",
            "price": 123.43153381347656,
            "change_pct": 3.4921989445066366,
            "composite_score": 0.23282026517902535,
            "volume_surge_ratio": 0
          }
        ]
      }
    }
  },
  "metadata": {
    "run_time": "2026-05-20T00:55:01.225442",
    "trigger_mode": "morning",
    "trade_date": "20240318",
    "selection_mode": "hybrid_3factor",
    "scoring_weights": {
      "momentum_signal": 0.2,
      "agent_fit_rr": 0.4,
      "quality_fundamental_technical": 0.4
    },
    "quality_gate_min": 40,
    "lookback_days": 10,
    "market": "IN",
    "min_market_cap_inr": 100000000000,
    "min_trading_value_inr": 1000000000,
    "filters": {
      "max_trigger_change_pct": 6.0,
      "max_entry_rsi": 60.0,
      "min_quality": 40
    },
    "regime": {
      "type": "bull_strong",
      "nifty_rsi": 49.1,
      "nifty_slope_pct": 1.63,
      "nifty_rvol": 10.9,
      "max_picks": 5
    }
  }
}