{
  "Value-to-Cap Ratio Top": [
    {
      "ticker": "IDFCFIRSTB",
      "name": "IDFCFIRSTB",
      "current_price": 72.80999755859375,
      "change_rate": 3.6884025816949295,
      "volume": 142273285,
      "trade_value": 10358917533.503113,
      "agent_fit_score": 1.0,
      "risk_reward_ratio": 3.6753207887543105,
      "stop_loss_pct": 5.0,
      "stop_loss_price": 69.16949768066407,
      "target_price": 86.19000244140625,
      "quality_score": 50.11666666666667,
      "quality_signal": "HOLD",
      "quality_reasons": "Expensive valuation (PE 36.0); Revenue declining (-1.1%); Earnings collapsing (-23.2%)",
      "final_score": 0.8004666666666668,
      "metrics": {
        "sector": "Financial Services",
        "industry": "Banks - Regional",
        "market_cap_cr": 58184.0,
        "trailing_pe": 36.0,
        "forward_pe": 10.4,
        "price_to_book": 1.24,
        "dividend_yield_pct": 37.0,
        "revenue_growth_pct": -1.1,
        "earnings_growth_pct": -23.2,
        "operating_margin_pct": 33.4,
        "profit_margin_pct": 32.8,
        "roe_pct": null,
        "rsi_14": 46.4,
        "sma_50": 65.69,
        "sma_200": 74.73,
        "pct_from_52w_high": -22.3,
        "beta": null,
        "analyst_recommendation": "hold",
        "target_mean": 75.06,
        "target_upside_pct": 11.0,
        "analyst_count": 18,
        "debt_to_equity": null,
        "valuation_score": 65.0,
        "growth_score": 15.0,
        "profitability_score": 90.0,
        "technical_score": 44.0,
        "analyst_score": 58.0,
        "risk_score": 50.0
      }
    },
    {
      "ticker": "INDUSINDBK",
      "name": "INDUSINDBK",
      "current_price": 964.5999755859375,
      "change_rate": 2.907131883474582,
      "volume": 8974624,
      "trade_value": 8656922091.292969,
      "agent_fit_score": 1.0,
      "risk_reward_ratio": 2.999999999999995,
      "stop_loss_pct": 5.0,
      "stop_loss_price": 916.3699768066406,
      "target_price": 1109.289971923828,
      "quality_score": 62.96666666666666,
      "quality_signal": "HOLD",
      "quality_reasons": "Expensive valuation (PE 78.1); Strong revenue growth (272.7%); Golden cross (50MA > 200MA)",
      "final_score": 0.7632692004380668,
      "metrics": {
        "sector": "Financial Services",
        "industry": "Banks - Regional",
        "market_cap_cr": 69508.0,
        "trailing_pe": 78.1,
        "forward_pe": 12.1,
        "price_to_book": 1.06,
        "dividend_yield_pct": 17.0,
        "revenue_growth_pct": 272.7,
        "earnings_growth_pct": null,
        "operating_margin_pct": 17.7,
        "profit_margin_pct": 5.2,
        "roe_pct": 1.4,
        "rsi_14": 49.0,
        "sma_50": 850.0,
        "sma_200": 836.59,
        "pct_from_52w_high": -7.9,
        "beta": 0.56,
        "analyst_recommendation": "hold",
        "target_mean": 877.33,
        "target_upside_pct": -1.7,
        "analyst_count": 36,
        "debt_to_equity": null,
        "valuation_score": 58.0,
        "growth_score": 90.0,
        "profitability_score": 50.0,
        "technical_score": 65.0,
        "analyst_score": 52.0,
        "risk_score": 75.0
      }
    },
    {
      "ticker": "RELIANCE",
      "name": "RELIANCE",
      "current_price": 1406.800048828125,
      "change_rate": 0.5934965197086164,
      "volume": 16683858,
      "trade_value": 23470852249.041504,
      "agent_fit_score": 1.0,
      "risk_reward_ratio": 2.9999999999999933,
      "stop_loss_pct": 5.0,
      "stop_loss_price": 1336.4600463867187,
      "target_price": 1617.8200561523436,
      "quality_score": 53.3,
      "quality_signal": "HOLD",
      "quality_reasons": "Death cross (50MA < 200MA); Analyst: Strong Buy; Target ₹1,697 (+27% upside)",
      "final_score": 0.6966721268811962,
      "metrics": {
        "sector": "Energy",
        "industry": "Oil & Gas Refining & Marketing",
        "market_cap_cr": 1807803.0,
        "trailing_pe": 22.4,
        "forward_pe": 18.6,
        "price_to_book": 2.0,
        "dividend_yield_pct": 41.0,
        "revenue_growth_pct": 12.5,
        "earnings_growth_pct": -12.6,
        "operating_margin_pct": 10.0,
        "profit_margin_pct": 7.6,
        "roe_pct": 9.1,
        "rsi_14": 38.7,
        "sma_50": 1378.09,
        "sma_200": 1431.54,
        "pct_from_52w_high": -17.1,
        "beta": 0.24,
        "analyst_recommendation": "strong_buy",
        "target_mean": 1696.62,
        "target_upside_pct": 27.0,
        "analyst_count": 32,
        "debt_to_equity": 36.7,
        "valuation_score": 72.0,
        "growth_score": 38.0,
        "profitability_score": 52.0,
        "technical_score": 42.0,
        "analyst_score": 80.0,
        "risk_score": 78.0
      }
    },
    {
      "ticker": "BHARTIARTL",
      "name": "BHARTIARTL",
      "current_price": 1929.5999755859375,
      "change_rate": 0.8466578324015589,
      "volume": 10795028,
      "trade_value": 20830085765.24951,
      "agent_fit_score": 1.0,
      "risk_reward_ratio": 2.999999999999998,
      "stop_loss_pct": 5.0,
      "stop_loss_price": 1833.1199768066406,
      "target_price": 2219.039971923828,
      "quality_score": 53.541666666666664,
      "quality_signal": "HOLD",
      "quality_reasons": "Expensive valuation (PE 43.7); Strong revenue growth (15.7%); Earnings collapsing (-34.0%)",
      "final_score": 0.6847463099221383,
      "metrics": {
        "sector": "Communication Services",
        "industry": "Telecom Services",
        "market_cap_cr": 1180588.0,
        "trailing_pe": 43.7,
        "forward_pe": 23.2,
        "price_to_book": 7.6,
        "dividend_yield_pct": 84.0,
        "revenue_growth_pct": 15.7,
        "earnings_growth_pct": -34.0,
        "operating_margin_pct": 32.2,
        "profit_margin_pct": 12.7,
        "roe_pct": 19.4,
        "rsi_14": 59.2,
        "sma_50": 1830.88,
        "sma_200": 1960.17,
        "pct_from_52w_high": -10.9,
        "beta": 0.04,
        "analyst_recommendation": "buy",
        "target_mean": 2292.13,
        "target_upside_pct": 18.3,
        "analyst_count": 31,
        "debt_to_equity": 99.7,
        "valuation_score": 45.0,
        "growth_score": 45.0,
        "profitability_score": 77.0,
        "technical_score": 45.0,
        "analyst_score": 77.0,
        "risk_score": 68.0
      }
    },
    {
      "ticker": "BANDHANBNK",
      "name": "BANDHANBNK",
      "current_price": 186.10000610351562,
      "change_rate": 1.7607180308019272,
      "volume": 19052653,
      "trade_value": 3545698839.5881653,
      "agent_fit_score": 1.0,
      "risk_reward_ratio": 2.999999999999997,
      "stop_loss_pct": 5.0,
      "stop_loss_price": 176.79500579833984,
      "target_price": 214.01500701904294,
      "quality_score": 66.55000000000001,
      "quality_signal": "HOLD",
      "quality_reasons": "Strong revenue growth (119.3%); Golden cross (50MA > 200MA); Analyst: None",
      "final_score": 0.6662000000000001,
      "metrics": {
        "sector": "Financial Services",
        "industry": "Banks - Regional",
        "market_cap_cr": 30664.0,
        "trailing_pe": 25.1,
        "forward_pe": 8.8,
        "price_to_book": 1.2,
        "dividend_yield_pct": 77.0,
        "revenue_growth_pct": 119.3,
        "earnings_growth_pct": 68.0,
        "operating_margin_pct": 26.4,
        "profit_margin_pct": 13.0,
        "roe_pct": 4.9,
        "rsi_14": 56.0,
        "sma_50": 173.69,
        "sma_200": 162.43,
        "pct_from_52w_high": -10.5,
        "beta": 0.8,
        "analyst_recommendation": "none",
        "target_mean": 188.67,
        "target_upside_pct": -0.9,
        "analyst_count": 24,
        "debt_to_equity": null,
        "valuation_score": 72.0,
        "growth_score": 90.0,
        "profitability_score": 62.0,
        "technical_score": 67.0,
        "analyst_score": 60.0,
        "risk_score": 60.0
      }
    }
  ],
  "screening_summary": {
    "total_tickers_scanned": 288,
    "snapshot_count": 286,
    "prev_snapshot_count": 286,
    "baseline_count": 286,
    "market_cap_count": 50,
    "triggers": {
      "Gap Up Momentum Top": {
        "candidate_count": 2,
        "top_candidates": [
          {
            "ticker": "KSB",
            "name": "KSB",
            "price": 779.4999389648438,
            "change_pct": 9.238597984025965,
            "composite_score": 0.9050119347897114,
            "volume_surge_ratio": 0
          },
          {
            "ticker": "J&KBANK",
            "name": "J&KBANK",
            "price": 121.2300033569336,
            "change_pct": 7.942307890876899,
            "composite_score": 0.5263496507901928,
            "volume_surge_ratio": 0
          }
        ]
      },
      "Value-to-Cap Ratio Top": {
        "candidate_count": 7,
        "top_candidates": [
          {
            "ticker": "KSB",
            "name": "KSB",
            "price": 779.4999389648438,
            "change_pct": 9.238597984025965,
            "composite_score": 0.8820434483624243,
            "volume_surge_ratio": 0
          },
          {
            "ticker": "J&KBANK",
            "name": "J&KBANK",
            "price": 121.2300033569336,
            "change_pct": 7.942307890876899,
            "composite_score": 0.46873340374495376,
            "volume_surge_ratio": 0
          },
          {
            "ticker": "IDFCFIRSTB",
            "name": "IDFCFIRSTB",
            "price": 72.80999755859375,
            "change_pct": 3.6884025816949295,
            "composite_score": 0.40263317104616037,
            "volume_surge_ratio": 0
          },
          {
            "ticker": "INDUSINDBK",
            "name": "INDUSINDBK",
            "price": 964.5999755859375,
            "change_pct": 2.907131883474582,
            "composite_score": 0.35454856587815253,
            "volume_surge_ratio": 0
          },
          {
            "ticker": "RELIANCE",
            "name": "RELIANCE",
            "price": 1406.800048828125,
            "change_pct": 0.5934965197086164,
            "composite_score": 0.3393898638896331,
            "volume_surge_ratio": 0
          },
          {
            "ticker": "BHARTIARTL",
            "name": "BHARTIARTL",
            "price": 1929.5999755859375,
            "change_pct": 0.8466578324015589,
            "composite_score": 0.33239271136183485,
            "volume_surge_ratio": 0
          },
          {
            "ticker": "BANDHANBNK",
            "name": "BANDHANBNK",
            "price": 186.10000610351562,
            "change_pct": 1.7607180308019272,
            "composite_score": 0.29408694006492775,
            "volume_surge_ratio": 0
          }
        ]
      }
    }
  },
  "metadata": {
    "run_time": "2026-05-19T04:46:40.799589",
    "trigger_mode": "morning",
    "trade_date": "20260226",
    "selection_mode": "hybrid_3factor",
    "scoring_weights": {
      "momentum_signal": 0.2,
      "agent_fit_rr": 0.4,
      "quality_fundamental_technical": 0.4
    },
    "quality_gate_min": 40,
    "lookback_days": 10,
    "market": "IN",
    "min_market_cap_inr": 100000000000,
    "min_trading_value_inr": 1000000000,
    "filters": {
      "max_trigger_change_pct": 6.0,
      "max_entry_rsi": 60.0
    }
  }
}