{
  "Value-to-Cap Ratio Top": [
    {
      "ticker": "PETRONET",
      "name": "PETRONET",
      "current_price": 265.1408386230469,
      "change_rate": 3.684031642232638,
      "volume": 11248413,
      "trade_value": 2982413655.9983826,
      "agent_fit_score": 1.0,
      "risk_reward_ratio": 3.0,
      "stop_loss_pct": 5.0,
      "stop_loss_price": 251.88379669189453,
      "target_price": 304.9119644165039,
      "quality_score": 56.91666666666667,
      "quality_signal": "HOLD",
      "quality_reasons": "Attractively valued (PE 10.2); Revenue declining (-23.3%); Death cross (50MA < 200MA)",
      "final_score": 0.8276666666666668,
      "metrics": {
        "sector": "Energy",
        "industry": "Oil & Gas Refining & Marketing",
        "market_cap_cr": 39773.0,
        "trailing_pe": 10.2,
        "forward_pe": 9.4,
        "price_to_book": 1.88,
        "dividend_yield_pct": 377.0,
        "revenue_growth_pct": -23.3,
        "earnings_growth_pct": 25.3,
        "operating_margin_pct": 17.5,
        "profit_margin_pct": 9.0,
        "roe_pct": 18.6,
        "rsi_14": 40.3,
        "sma_50": 270.16,
        "sma_200": 278.87,
        "pct_from_52w_high": -18.8,
        "beta": 0.5,
        "analyst_recommendation": "buy",
        "target_mean": 314.61,
        "target_upside_pct": 18.7,
        "analyst_count": 31,
        "debt_to_equity": 10.5,
        "valuation_score": 78.0,
        "growth_score": 45.0,
        "profitability_score": 65.0,
        "technical_score": 45.0,
        "analyst_score": 72.0,
        "risk_score": 80.0
      }
    },
    {
      "ticker": "GAIL",
      "name": "GAIL",
      "current_price": 175.68943786621094,
      "change_rate": 3.16420882996974,
      "volume": 40868454,
      "trade_value": 7180155709.7211,
      "agent_fit_score": 1.0,
      "risk_reward_ratio": 2.999999999999997,
      "stop_loss_pct": 5.0,
      "stop_loss_price": 166.90496597290038,
      "target_price": 202.04285354614257,
      "quality_score": 50.866666666666674,
      "quality_signal": "HOLD",
      "quality_reasons": "Attractively valued (PE 12.0); Revenue declining (-4.5%); Earnings collapsing (-57.0%)",
      "final_score": 0.789238218705522,
      "metrics": {
        "sector": "Utilities",
        "industry": "Utilities - Regulated Gas",
        "market_cap_cr": 102650.0,
        "trailing_pe": 12.0,
        "forward_pe": 9.7,
        "price_to_book": 1.16,
        "dividend_yield_pct": 780.0,
        "revenue_growth_pct": -4.5,
        "earnings_growth_pct": -57.0,
        "operating_margin_pct": 4.9,
        "profit_margin_pct": 6.0,
        "roe_pct": null,
        "rsi_14": 48.2,
        "sma_50": 153.69,
        "sma_200": 167.96,
        "pct_from_52w_high": -23.0,
        "beta": 0.6,
        "analyst_recommendation": "buy",
        "target_mean": 187.48,
        "target_upside_pct": 20.1,
        "analyst_count": 31,
        "debt_to_equity": 25.4,
        "valuation_score": 83.0,
        "growth_score": 15.0,
        "profitability_score": 42.0,
        "technical_score": 44.0,
        "analyst_score": 77.0,
        "risk_score": 72.0
      }
    },
    {
      "ticker": "ENGINERSIN",
      "name": "ENGINERSIN",
      "current_price": 212.40701293945312,
      "change_rate": 1.2141946297452382,
      "volume": 11335110,
      "trade_value": 2407656856.4401245,
      "agent_fit_score": 1.0,
      "risk_reward_ratio": 2.9999999999999947,
      "stop_loss_pct": 5.0,
      "stop_loss_price": 201.78666229248046,
      "target_price": 244.26806488037107,
      "quality_score": 65.525,
      "quality_signal": "HOLD",
      "quality_reasons": "Strong revenue growth (58.3%); Highly profitable (margin 19.3%); Golden cross (50MA > 200MA)",
      "final_score": 0.749924811599775,
      "metrics": {
        "sector": "Industrials",
        "industry": "Engineering & Construction",
        "market_cap_cr": 13770.0,
        "trailing_pe": 17.8,
        "forward_pe": 20.8,
        "price_to_book": 5.07,
        "dividend_yield_pct": 126.0,
        "revenue_growth_pct": 58.3,
        "earnings_growth_pct": 218.6,
        "operating_margin_pct": 28.3,
        "profit_margin_pct": 19.3,
        "roe_pct": null,
        "rsi_14": 47.7,
        "sma_50": 221.31,
        "sma_200": 203.46,
        "pct_from_52w_high": -8.2,
        "beta": 1.03,
        "analyst_recommendation": "none",
        "target_mean": 247.0,
        "target_upside_pct": 0.8,
        "analyst_count": 5,
        "debt_to_equity": 0.7,
        "valuation_score": 50.0,
        "growth_score": 90.0,
        "profitability_score": 80.0,
        "technical_score": 67.0,
        "analyst_score": 50.0,
        "risk_score": 72.0
      }
    },
    {
      "ticker": "CENTRALBK",
      "name": "CENTRALBK",
      "current_price": 63.22727584838867,
      "change_rate": 3.7974704947520586,
      "volume": 32063126,
      "trade_value": 2027264112.163643,
      "agent_fit_score": 1.0,
      "risk_reward_ratio": 2.9999999999999956,
      "stop_loss_pct": 5.0,
      "stop_loss_price": 60.065912055969235,
      "target_price": 72.71136722564697,
      "quality_score": 56.90833333333333,
      "quality_signal": "HOLD",
      "quality_reasons": "Attractively valued (PE 6.8); Strong revenue growth (44.8%); Earnings collapsing (-35.4%)",
      "final_score": 0.7211837312078822,
      "metrics": {
        "sector": "Financial Services",
        "industry": "Banks - Regional",
        "market_cap_cr": 30811.0,
        "trailing_pe": 6.8,
        "forward_pe": null,
        "price_to_book": 0.79,
        "dividend_yield_pct": 411.0,
        "revenue_growth_pct": 44.8,
        "earnings_growth_pct": -35.4,
        "operating_margin_pct": 34.4,
        "profit_margin_pct": 24.4,
        "roe_pct": 11.9,
        "rsi_14": 39.7,
        "sma_50": 35.08,
        "sma_200": 36.87,
        "pct_from_52w_high": -17.4,
        "beta": 0.52,
        "analyst_recommendation": "none",
        "target_mean": null,
        "target_upside_pct": null,
        "analyst_count": 0,
        "debt_to_equity": null,
        "valuation_score": 90.0,
        "growth_score": 52.0,
        "profitability_score": 77.0,
        "technical_score": 42.0,
        "analyst_score": 50.0,
        "risk_score": 75.0
      }
    },
    {
      "ticker": "ABCAPITAL",
      "name": "ABCAPITAL",
      "current_price": 204.1999969482422,
      "change_rate": 1.5667713746184069,
      "volume": 15770069,
      "trade_value": 3220248041.6735687,
      "agent_fit_score": 1.0,
      "risk_reward_ratio": 2.9999999999999942,
      "stop_loss_pct": 5.0,
      "stop_loss_price": 193.98999710083007,
      "target_price": 234.8299964904785,
      "quality_score": 62.85,
      "quality_signal": "HOLD",
      "quality_reasons": "Golden cross (50MA > 200MA); Analyst: Strong Buy; Target ₹411 (+17% upside)",
      "final_score": 0.6514,
      "metrics": {
        "sector": "Financial Services",
        "industry": "Financial Conglomerates",
        "market_cap_cr": 92043.0,
        "trailing_pe": 24.6,
        "forward_pe": 14.3,
        "price_to_book": 2.67,
        "dividend_yield_pct": null,
        "revenue_growth_pct": 7.7,
        "earnings_growth_pct": 30.1,
        "operating_margin_pct": 13.7,
        "profit_margin_pct": 11.6,
        "roe_pct": 11.2,
        "rsi_14": 52.4,
        "sma_50": 331.42,
        "sma_200": 326.88,
        "pct_from_52w_high": -6.6,
        "beta": 0.71,
        "analyst_recommendation": "strong_buy",
        "target_mean": 411.42,
        "target_upside_pct": 17.1,
        "analyst_count": 12,
        "debt_to_equity": 491.7,
        "valuation_score": 65.0,
        "growth_score": 65.0,
        "profitability_score": 58.0,
        "technical_score": 67.0,
        "analyst_score": 77.0,
        "risk_score": 45.0
      }
    }
  ],
  "screening_summary": {
    "total_tickers_scanned": 288,
    "snapshot_count": 283,
    "prev_snapshot_count": 283,
    "baseline_count": 283,
    "market_cap_count": 50,
    "triggers": {
      "Gap Up Momentum Top": {
        "candidate_count": 0,
        "top_candidates": []
      },
      "Value-to-Cap Ratio Top": {
        "candidate_count": 9,
        "top_candidates": [
          {
            "ticker": "JSWENERGY",
            "name": "JSWENERGY",
            "price": 577.1599731445312,
            "change_pct": 7.220576414733963,
            "composite_score": 0.8764198999411611,
            "volume_surge_ratio": 0
          },
          {
            "ticker": "PNB",
            "name": "PNB",
            "price": 129.8107452392578,
            "change_pct": 6.669297263809083,
            "composite_score": 0.7124977660747852,
            "volume_surge_ratio": 0
          },
          {
            "ticker": "SAIL",
            "name": "SAIL",
            "price": 145.2366180419922,
            "change_pct": 0.2367164506980966,
            "composite_score": 0.6024533474453396,
            "volume_surge_ratio": 0
          },
          {
            "ticker": "YESBANK",
            "name": "YESBANK",
            "price": 25.399999618530273,
            "change_pct": 3.2520293685164203,
            "composite_score": 0.5501605352223968,
            "volume_surge_ratio": 0
          },
          {
            "ticker": "PETRONET",
            "name": "PETRONET",
            "price": 265.1408386230469,
            "change_pct": 3.684031642232638,
            "composite_score": 0.5102245139187975,
            "volume_surge_ratio": 0
          },
          {
            "ticker": "GAIL",
            "name": "GAIL",
            "price": 175.68943786621094,
            "change_pct": 3.16420882996974,
            "composite_score": 0.5006658349538806,
            "volume_surge_ratio": 0
          },
          {
            "ticker": "CENTRALBK",
            "name": "CENTRALBK",
            "price": 63.22727584838867,
            "change_pct": 3.7974704947520586,
            "composite_score": 0.4387116141676105,
            "volume_surge_ratio": 0
          },
          {
            "ticker": "ENGINERSIN",
            "name": "ENGINERSIN",
            "price": 212.40701293945312,
            "change_pct": 1.2141946297452382,
            "composite_score": 0.4348651622400388,
            "volume_surge_ratio": 0
          },
          {
            "ticker": "ABCAPITAL",
            "name": "ABCAPITAL",
            "price": 204.1999969482422,
            "change_pct": 1.5667713746184069,
            "composite_score": 0.3758644067444957,
            "volume_surge_ratio": 0
          }
        ]
      }
    }
  },
  "metadata": {
    "run_time": "2026-05-20T01:10:51.579121",
    "trigger_mode": "morning",
    "trade_date": "20240403",
    "selection_mode": "hybrid_3factor",
    "scoring_weights": {
      "momentum_signal": 0.2,
      "agent_fit_rr": 0.4,
      "quality_fundamental_technical": 0.4
    },
    "quality_gate_min": 40,
    "lookback_days": 10,
    "market": "IN",
    "min_market_cap_inr": 100000000000,
    "min_trading_value_inr": 1000000000,
    "filters": {
      "max_trigger_change_pct": 6.0,
      "max_entry_rsi": 60.0,
      "min_quality": 40
    },
    "regime": {
      "type": "bull_strong",
      "nifty_rsi": 59.9,
      "nifty_slope_pct": 1.07,
      "nifty_rvol": 9.8,
      "max_picks": 5
    }
  }
}