{
  "Gap Up Momentum Top": [
    {
      "ticker": "IDFCFIRSTB",
      "name": "IDFCFIRSTB",
      "current_price": 82.23085021972656,
      "change_rate": 2.2938612267675986,
      "volume": 86003143,
      "trade_value": 7072111570.458725,
      "agent_fit_score": 1.0,
      "risk_reward_ratio": 3.0,
      "stop_loss_pct": 5.0,
      "stop_loss_price": 78.11930770874024,
      "target_price": 94.56547775268554,
      "quality_score": 50.11666666666667,
      "quality_signal": "HOLD",
      "quality_reasons": "Expensive valuation (PE 36.1); Revenue declining (-1.1%); Earnings collapsing (-23.2%)",
      "final_score": 0.8004666666666668,
      "metrics": {
        "sector": "Financial Services",
        "industry": "Banks - Regional",
        "market_cap_cr": 58373.0,
        "trailing_pe": 36.1,
        "forward_pe": 10.5,
        "price_to_book": 1.24,
        "dividend_yield_pct": 37.0,
        "revenue_growth_pct": -1.1,
        "earnings_growth_pct": -23.2,
        "operating_margin_pct": 33.4,
        "profit_margin_pct": 32.8,
        "roe_pct": null,
        "rsi_14": 46.2,
        "sma_50": 65.71,
        "sma_200": 74.72,
        "pct_from_52w_high": -22.1,
        "beta": null,
        "analyst_recommendation": "hold",
        "target_mean": 75.06,
        "target_upside_pct": 10.7,
        "analyst_count": 18,
        "debt_to_equity": null,
        "valuation_score": 65.0,
        "growth_score": 15.0,
        "profitability_score": 90.0,
        "technical_score": 44.0,
        "analyst_score": 58.0,
        "risk_score": 50.0
      }
    }
  ],
  "Value-to-Cap Ratio Top": [
    {
      "ticker": "IRB",
      "name": "IRB",
      "current_price": 34.593170166015625,
      "change_rate": 4.166646564797285,
      "volume": 195509508,
      "trade_value": 6763293679.317993,
      "agent_fit_score": 1.0,
      "risk_reward_ratio": 3.0,
      "stop_loss_pct": 5.0,
      "stop_loss_price": 32.863511657714845,
      "target_price": 39.782145690917964,
      "quality_score": 50.625,
      "quality_signal": "HOLD",
      "quality_reasons": "Revenue declining (-16.3%); Earnings collapsing (-96.5%); Death cross (50MA < 200MA)",
      "final_score": 0.8025000000000001,
      "metrics": {
        "sector": "Industrials",
        "industry": "Infrastructure Operations",
        "market_cap_cr": 24410.0,
        "trailing_pe": 32.1,
        "forward_pe": 21.6,
        "price_to_book": 1.21,
        "dividend_yield_pct": 69.0,
        "revenue_growth_pct": -16.3,
        "earnings_growth_pct": -96.5,
        "operating_margin_pct": 23.6,
        "profit_margin_pct": 11.6,
        "roe_pct": null,
        "rsi_14": 33.5,
        "sma_50": 21.26,
        "sma_200": 21.26,
        "pct_from_52w_high": -25.5,
        "beta": -0.09,
        "analyst_recommendation": "none",
        "target_mean": 28.5,
        "target_upside_pct": 41.0,
        "analyst_count": 5,
        "debt_to_equity": 102.3,
        "valuation_score": 65.0,
        "growth_score": 15.0,
        "profitability_score": 72.0,
        "technical_score": 45.0,
        "analyst_score": 72.0,
        "risk_score": 58.0
      }
    },
    {
      "ticker": "IIFL",
      "name": "IIFL",
      "current_price": 421.72955322265625,
      "change_rate": 5.881621004155126,
      "volume": 11996177,
      "trade_value": 5059142366.589905,
      "agent_fit_score": 1.0,
      "risk_reward_ratio": 2.9999999999999947,
      "stop_loss_pct": 5.0,
      "stop_loss_price": 400.6430755615234,
      "target_price": 484.9889862060547,
      "quality_score": 56.69166666666667,
      "quality_signal": "HOLD",
      "quality_reasons": "Attractively valued (PE 11.9); Revenue declining (-14.1%); Highly profitable (margin 21.0%)",
      "final_score": 0.7874596872546258,
      "metrics": {
        "sector": "Financial Services",
        "industry": "Credit Services",
        "market_cap_cr": 19595.0,
        "trailing_pe": 11.9,
        "forward_pe": 6.9,
        "price_to_book": 1.41,
        "dividend_yield_pct": 88.0,
        "revenue_growth_pct": -14.1,
        "earnings_growth_pct": 183.1,
        "operating_margin_pct": 39.8,
        "profit_margin_pct": 21.0,
        "roe_pct": 12.3,
        "rsi_14": 49.6,
        "sma_50": 456.06,
        "sma_200": 504.6,
        "pct_from_52w_high": -31.7,
        "beta": 0.25,
        "analyst_recommendation": "strong_buy",
        "target_mean": 617.5,
        "target_upside_pct": 34.0,
        "analyst_count": 4,
        "debt_to_equity": 446.2,
        "valuation_score": 83.0,
        "growth_score": 52.0,
        "profitability_score": 77.0,
        "technical_score": 41.0,
        "analyst_score": 75.0,
        "risk_score": 50.0
      }
    },
    {
      "ticker": "GAIL",
      "name": "GAIL",
      "current_price": 186.51324462890625,
      "change_rate": 5.2424613513736205,
      "volume": 56272730,
      "trade_value": 10495609456.426392,
      "agent_fit_score": 1.0,
      "risk_reward_ratio": 3.0,
      "stop_loss_pct": 5.0,
      "stop_loss_price": 177.18758239746094,
      "target_price": 214.49023132324217,
      "quality_score": 50.866666666666674,
      "quality_signal": "HOLD",
      "quality_reasons": "Attractively valued (PE 12.0); Revenue declining (-4.5%); Earnings collapsing (-57.0%)",
      "final_score": 0.7582504871365399,
      "metrics": {
        "sector": "Utilities",
        "industry": "Utilities - Regulated Gas",
        "market_cap_cr": 102650.0,
        "trailing_pe": 12.0,
        "forward_pe": 9.7,
        "price_to_book": 1.16,
        "dividend_yield_pct": 780.0,
        "revenue_growth_pct": -4.5,
        "earnings_growth_pct": -57.0,
        "operating_margin_pct": 4.9,
        "profit_margin_pct": 6.0,
        "roe_pct": null,
        "rsi_14": 48.2,
        "sma_50": 153.69,
        "sma_200": 167.96,
        "pct_from_52w_high": -23.0,
        "beta": 0.6,
        "analyst_recommendation": "buy",
        "target_mean": 187.48,
        "target_upside_pct": 20.1,
        "analyst_count": 31,
        "debt_to_equity": 25.4,
        "valuation_score": 83.0,
        "growth_score": 15.0,
        "profitability_score": 42.0,
        "technical_score": 44.0,
        "analyst_score": 77.0,
        "risk_score": 72.0
      }
    },
    {
      "ticker": "INDUSTOWER",
      "name": "INDUSTOWER",
      "current_price": 327.79998779296875,
      "change_rate": 4.394900571009156,
      "volume": 28736885,
      "trade_value": 9419950552.207947,
      "agent_fit_score": 1.0,
      "risk_reward_ratio": 2.9999999999999964,
      "stop_loss_pct": 5.0,
      "stop_loss_price": 311.4099884033203,
      "target_price": 376.969985961914,
      "quality_score": 61.791666666666664,
      "quality_signal": "HOLD",
      "quality_reasons": "Highly profitable (margin 22.0%); Golden cross (50MA > 200MA); Analyst: Hold",
      "final_score": 0.7147256020443548,
      "metrics": {
        "sector": "Communication Services",
        "industry": "Telecom Services",
        "market_cap_cr": 113584.0,
        "trailing_pe": 15.9,
        "forward_pe": 13.8,
        "price_to_book": 2.86,
        "dividend_yield_pct": null,
        "revenue_growth_pct": 4.8,
        "earnings_growth_pct": 0.8,
        "operating_margin_pct": 32.4,
        "profit_margin_pct": 22.0,
        "roe_pct": 19.8,
        "rsi_14": 59.0,
        "sma_50": 421.01,
        "sma_200": 403.1,
        "pct_from_52w_high": -10.6,
        "beta": 0.02,
        "analyst_recommendation": "hold",
        "target_mean": 452.8,
        "target_upside_pct": 5.1,
        "analyst_count": 25,
        "debt_to_equity": 53.3,
        "valuation_score": 67.0,
        "growth_score": 40.0,
        "profitability_score": 83.0,
        "technical_score": 65.0,
        "analyst_score": 62.0,
        "risk_score": 68.0
      }
    }
  ],
  "screening_summary": {
    "total_tickers_scanned": 288,
    "snapshot_count": 283,
    "prev_snapshot_count": 283,
    "baseline_count": 283,
    "market_cap_count": 50,
    "triggers": {
      "Gap Up Momentum Top": {
        "candidate_count": 3,
        "top_candidates": [
          {
            "ticker": "NAUKRI",
            "name": "NAUKRI",
            "price": 1233.0838623046875,
            "change_pct": 9.70543461722378,
            "composite_score": 0.765910520653978,
            "volume_surge_ratio": 0
          },
          {
            "ticker": "IDFCFIRSTB",
            "name": "IDFCFIRSTB",
            "price": 82.23085021972656,
            "change_pct": 2.2938612267675986,
            "composite_score": 0.45286892257265365,
            "volume_surge_ratio": 0
          },
          {
            "ticker": "HINDCOPPER",
            "name": "HINDCOPPER",
            "price": 328.1768798828125,
            "change_pct": 2.7760534863261697,
            "composite_score": 0.2205383758922338,
            "volume_surge_ratio": 0
          }
        ]
      },
      "Value-to-Cap Ratio Top": {
        "candidate_count": 7,
        "top_candidates": [
          {
            "ticker": "EXIDEIND",
            "name": "EXIDEIND",
            "price": 373.79510498046875,
            "change_pct": 17.181913304167292,
            "composite_score": 1.15,
            "volume_surge_ratio": 0
          },
          {
            "ticker": "NAUKRI",
            "name": "NAUKRI",
            "price": 1233.0838623046875,
            "change_pct": 9.70543461722378,
            "composite_score": 0.4277773181764335,
            "volume_surge_ratio": 0
          },
          {
            "ticker": "IRB",
            "name": "IRB",
            "price": 34.593170166015625,
            "change_pct": 4.166646564797285,
            "composite_score": 0.38933869935345694,
            "volume_surge_ratio": 0
          },
          {
            "ticker": "IIFL",
            "name": "IIFL",
            "price": 421.72955322265625,
            "change_pct": 5.881621004155126,
            "composite_score": 0.36948970558896577,
            "volume_surge_ratio": 0
          },
          {
            "ticker": "GAIL",
            "name": "GAIL",
            "price": 186.51324462890625,
            "change_pct": 5.2424613513736205,
            "composite_score": 0.36650571450006797,
            "volume_surge_ratio": 0
          },
          {
            "ticker": "INDUSTOWER",
            "name": "INDUSTOWER",
            "price": 327.79998779296875,
            "change_pct": 4.394900571009156,
            "composite_score": 0.32245943503009467,
            "volume_surge_ratio": 0
          },
          {
            "ticker": "IDFCFIRSTB",
            "name": "IDFCFIRSTB",
            "price": 82.23085021972656,
            "change_pct": 2.2938612267675986,
            "composite_score": 0.28834394441987976,
            "volume_surge_ratio": 0
          }
        ]
      }
    }
  },
  "metadata": {
    "run_time": "2026-05-20T01:15:13.274646",
    "trigger_mode": "morning",
    "trade_date": "20240408",
    "selection_mode": "hybrid_3factor",
    "scoring_weights": {
      "momentum_signal": 0.2,
      "agent_fit_rr": 0.4,
      "quality_fundamental_technical": 0.4
    },
    "quality_gate_min": 40,
    "lookback_days": 10,
    "market": "IN",
    "min_market_cap_inr": 100000000000,
    "min_trading_value_inr": 1000000000,
    "filters": {
      "max_trigger_change_pct": 6.0,
      "max_entry_rsi": 60.0,
      "min_quality": 40
    },
    "regime": {
      "type": "bull_strong",
      "nifty_rsi": 65.9,
      "nifty_slope_pct": 1.05,
      "nifty_rvol": 9.9,
      "max_picks": 5
    }
  }
}