{
  "Gap Up Momentum Top": [
    {
      "ticker": "DLF",
      "name": "DLF",
      "current_price": 769.5214233398438,
      "change_rate": 2.8732587389330075,
      "volume": 8436181,
      "trade_value": 6491822010.672546,
      "agent_fit_score": 1.0,
      "risk_reward_ratio": 2.9999999999999942,
      "stop_loss_pct": 5.0,
      "stop_loss_price": 731.0453521728515,
      "target_price": 884.9496368408203,
      "quality_score": 51.56666666666667,
      "quality_signal": "HOLD",
      "quality_reasons": "Revenue declining (-42.0%); Highly profitable (margin 53.9%); Death cross (50MA < 200MA)",
      "final_score": 0.6062666666666667,
      "metrics": {
        "sector": "Real Estate",
        "industry": "Real Estate - Development",
        "market_cap_cr": 142925.0,
        "trailing_pe": 32.4,
        "forward_pe": 21.6,
        "price_to_book": 3.15,
        "dividend_yield_pct": 105.0,
        "revenue_growth_pct": -42.0,
        "earnings_growth_pct": -1.1,
        "operating_margin_pct": 20.0,
        "profit_margin_pct": 53.9,
        "roe_pct": 10.0,
        "rsi_14": 47.6,
        "sma_50": 565.97,
        "sma_200": 671.67,
        "pct_from_52w_high": -34.9,
        "beta": 0.34,
        "analyst_recommendation": "strong_buy",
        "target_mean": 821.91,
        "target_upside_pct": 42.3,
        "analyst_count": 22,
        "debt_to_equity": 0.7,
        "valuation_score": 58.0,
        "growth_score": 15.0,
        "profitability_score": 72.0,
        "technical_score": 41.0,
        "analyst_score": 85.0,
        "risk_score": 85.0
      }
    }
  ],
  "Value-to-Cap Ratio Top": [
    {
      "ticker": "ENGINERSIN",
      "name": "ENGINERSIN",
      "current_price": 199.24856567382812,
      "change_rate": 4.583258514419134,
      "volume": 11527180,
      "trade_value": 2296774081.264038,
      "agent_fit_score": 1.0,
      "risk_reward_ratio": 2.9999999999999942,
      "stop_loss_pct": 5.0,
      "stop_loss_price": 189.2861373901367,
      "target_price": 229.13585052490234,
      "quality_score": 65.525,
      "quality_signal": "HOLD",
      "quality_reasons": "Strong revenue growth (58.3%); Highly profitable (margin 19.3%); Golden cross (50MA > 200MA)",
      "final_score": 0.8621000000000001,
      "metrics": {
        "sector": "Industrials",
        "industry": "Engineering & Construction",
        "market_cap_cr": 13770.0,
        "trailing_pe": 17.8,
        "forward_pe": 20.8,
        "price_to_book": 5.07,
        "dividend_yield_pct": 126.0,
        "revenue_growth_pct": 58.3,
        "earnings_growth_pct": 218.6,
        "operating_margin_pct": 28.3,
        "profit_margin_pct": 19.3,
        "roe_pct": null,
        "rsi_14": 52.4,
        "sma_50": 221.31,
        "sma_200": 203.46,
        "pct_from_52w_high": -8.2,
        "beta": 1.03,
        "analyst_recommendation": "none",
        "target_mean": 247.0,
        "target_upside_pct": 0.8,
        "analyst_count": 5,
        "debt_to_equity": 0.7,
        "valuation_score": 50.0,
        "growth_score": 90.0,
        "profitability_score": 80.0,
        "technical_score": 67.0,
        "analyst_score": 50.0,
        "risk_score": 72.0
      }
    },
    {
      "ticker": "ETERNAL",
      "name": "ETERNAL",
      "current_price": 229.97000122070312,
      "change_rate": 0.7403199800435251,
      "volume": 47166130,
      "trade_value": 10846794973.675842,
      "agent_fit_score": 1.0,
      "risk_reward_ratio": 2.9999999999999925,
      "stop_loss_pct": 5.0,
      "stop_loss_price": 218.47150115966795,
      "target_price": 264.46550140380856,
      "quality_score": 54.63333333333334,
      "quality_signal": "HOLD",
      "quality_reasons": "Expensive valuation (PE 633.9); Strong revenue growth (196.5%); Death cross (50MA < 200MA)",
      "final_score": 0.7465821990235038,
      "metrics": {
        "sector": "Consumer Cyclical",
        "industry": "Internet Retail",
        "market_cap_cr": 227282.0,
        "trailing_pe": 633.9,
        "forward_pe": 60.9,
        "price_to_book": 7.31,
        "dividend_yield_pct": null,
        "revenue_growth_pct": 196.5,
        "earnings_growth_pct": 375.0,
        "operating_margin_pct": 0.1,
        "profit_margin_pct": 0.7,
        "roe_pct": 1.2,
        "rsi_14": 49.5,
        "sma_50": 241.42,
        "sma_200": 288.59,
        "pct_from_52w_high": -32.9,
        "beta": 0.28,
        "analyst_recommendation": "buy",
        "target_mean": 346.97,
        "target_upside_pct": 40.4,
        "analyst_count": 32,
        "debt_to_equity": 14.8,
        "valuation_score": 45.0,
        "growth_score": 90.0,
        "profitability_score": 30.0,
        "technical_score": 41.0,
        "analyst_score": 82.0,
        "risk_score": 85.0
      }
    },
    {
      "ticker": "INDUSTOWER",
      "name": "INDUSTOWER",
      "current_price": 387.95001220703125,
      "change_rate": 0.3751648659847995,
      "volume": 13139198,
      "trade_value": 5097352024.490601,
      "agent_fit_score": 1.0,
      "risk_reward_ratio": 2.9999999999999942,
      "stop_loss_pct": 5.0,
      "stop_loss_price": 368.55251159667966,
      "target_price": 446.1425140380859,
      "quality_score": 61.791666666666664,
      "quality_signal": "HOLD",
      "quality_reasons": "Highly profitable (margin 22.0%); Golden cross (50MA > 200MA); Analyst: Hold",
      "final_score": 0.7013788248083307,
      "metrics": {
        "sector": "Communication Services",
        "industry": "Telecom Services",
        "market_cap_cr": 113584.0,
        "trailing_pe": 15.9,
        "forward_pe": 13.8,
        "price_to_book": 2.86,
        "dividend_yield_pct": null,
        "revenue_growth_pct": 4.8,
        "earnings_growth_pct": 0.8,
        "operating_margin_pct": 32.4,
        "profit_margin_pct": 22.0,
        "roe_pct": 19.8,
        "rsi_14": 58.9,
        "sma_50": 421.01,
        "sma_200": 403.1,
        "pct_from_52w_high": -10.6,
        "beta": 0.02,
        "analyst_recommendation": "hold",
        "target_mean": 452.8,
        "target_upside_pct": 5.1,
        "analyst_count": 25,
        "debt_to_equity": 53.3,
        "valuation_score": 67.0,
        "growth_score": 40.0,
        "profitability_score": 83.0,
        "technical_score": 65.0,
        "analyst_score": 62.0,
        "risk_score": 68.0
      }
    }
  ],
  "screening_summary": {
    "total_tickers_scanned": 288,
    "snapshot_count": 286,
    "prev_snapshot_count": 286,
    "baseline_count": 286,
    "market_cap_count": 50,
    "triggers": {
      "Gap Up Momentum Top": {
        "candidate_count": 1,
        "top_candidates": [
          {
            "ticker": "DLF",
            "name": "DLF",
            "price": 769.5214233398438,
            "change_pct": 2.8732587389330075,
            "composite_score": 0.15,
            "volume_surge_ratio": 0
          }
        ]
      },
      "Value-to-Cap Ratio Top": {
        "candidate_count": 6,
        "top_candidates": [
          {
            "ticker": "JKTYRE",
            "name": "JKTYRE",
            "price": 390.0447082519531,
            "change_pct": 13.107213038008794,
            "composite_score": 1.114584530392662,
            "volume_surge_ratio": 0
          },
          {
            "ticker": "ENGINERSIN",
            "name": "ENGINERSIN",
            "price": 199.24856567382812,
            "change_pct": 4.583258514419134,
            "composite_score": 0.3177193011780849,
            "volume_surge_ratio": 0
          },
          {
            "ticker": "DLF",
            "name": "DLF",
            "price": 769.5214233398438,
            "change_pct": 2.8732587389330075,
            "composite_score": 0.2910947729133079,
            "volume_surge_ratio": 0
          },
          {
            "ticker": "ETERNAL",
            "name": "ETERNAL",
            "price": 229.97000122070312,
            "change_pct": 0.7403199800435251,
            "composite_score": 0.2893300601930789,
            "volume_surge_ratio": 0
          },
          {
            "ticker": "INDUSTOWER",
            "name": "INDUSTOWER",
            "price": 387.95001220703125,
            "change_pct": 0.3751648659847995,
            "composite_score": 0.26019684215223987,
            "volume_surge_ratio": 0
          },
          {
            "ticker": "IRB",
            "name": "IRB",
            "price": 25.550243377685547,
            "change_pct": 3.2991336503581667,
            "composite_score": 0.23880674126552323,
            "volume_surge_ratio": 0
          }
        ]
      }
    }
  },
  "metadata": {
    "run_time": "2026-05-19T22:39:08.275979",
    "trigger_mode": "morning",
    "trade_date": "20250521",
    "selection_mode": "hybrid_3factor",
    "scoring_weights": {
      "momentum_signal": 0.2,
      "agent_fit_rr": 0.4,
      "quality_fundamental_technical": 0.4
    },
    "quality_gate_min": 40,
    "lookback_days": 10,
    "market": "IN",
    "min_market_cap_inr": 100000000000,
    "min_trading_value_inr": 1000000000,
    "filters": {
      "max_trigger_change_pct": 6.0,
      "max_entry_rsi": 60.0,
      "min_quality": 40
    },
    "regime": {
      "type": "bull_medium",
      "nifty_rsi": 59.9,
      "nifty_slope_pct": 2.75,
      "nifty_rvol": 17.5,
      "max_picks": 4
    }
  }
}